rockverse/__init__.py
rockverse/errors.py
rockverse/_assert/__init__.py
rockverse/_assert/condition.py
rockverse/_assert/iterable.py
rockverse/_utils/__init__.py
rockverse/_utils/logo.py
rockverse/configure/__init__.py
rockverse/configure/latex_strings.py
rockverse/configure/orthogonal_viewer.py
rockverse/dect/__init__.py
rockverse/dect/_corefunctions.py
rockverse/dect/_cpu_functions.py
rockverse/dect/_gpu_functions.py
rockverse/dect/_hash_functions.py
rockverse/dect/_periodic_table.py
rockverse/optimize/__init__.py
rockverse/optimize/gaussian.py
rockverse/region/__init__.py
rockverse/region/cylinder.py
rockverse/region/region.py
rockverse/region/sphere.py
rockverse/viz/__init__.py
rockverse/viz/orthogonal_slices.py
rockverse/voxel_image/__init__.py
rockverse/voxel_image/_finneypack.py
rockverse/voxel_image/_math.py
rockverse/voxel_image/histogram.py
rockverse-1.2.1.dist-info/licenses/LICENSE.md
rockverse-1.2.1.dist-info/METADATA
rockverse-1.2.1.dist-info/WHEEL
rockverse-1.2.1.dist-info/top_level.txt
rockverse-1.2.1.dist-info/RECORD
