Metadata-Version: 2.4
Name: rockverse
Version: 1.2.1
Summary: Python tools for Computational Petrophysics
Author-email: "Rodolfo A. Victor" <rodolfo@rodolfovictor.com>
Project-URL: Homepage, https://rockverse.readthedocs.io/
Project-URL: Documentation, https://rockverse.readthedocs.io/
Project-URL: Repository, https://github.com/rodolfovictor/rockverse
Project-URL: Issues, https://github.com/rodolfovictor/rockverse/issues
Project-URL: Changelog, https://github.com/rodolfovictor/rockverse/blob/main/Changelog.md
Project-URL: Official Website, https://rockverse.readthedocs.io/
Keywords: petrophysics,well,log,well log,digital rock
Classifier: Programming Language :: Python :: 3
Classifier: License :: OSI Approved :: MIT License
Classifier: Operating System :: OS Independent
Classifier: Development Status :: 4 - Beta
Classifier: Environment :: GPU
Classifier: Environment :: GPU :: NVIDIA CUDA
Classifier: Intended Audience :: Developers
Classifier: Intended Audience :: Science/Research
Classifier: Topic :: Scientific/Engineering
Requires-Python: <3.13,>=3.11
License-File: LICENSE.md
Requires-Dist: docutils>=0.17
Requires-Dist: ipympl
Requires-Dist: ipython
Requires-Dist: ipyparallel
Requires-Dist: ipywidgets
Requires-Dist: jupyter
Requires-Dist: jupyterlab
Requires-Dist: matplotlib>=3.10
Requires-Dist: mpi4py
Requires-Dist: myst-parser
Requires-Dist: nbsphinx
Requires-Dist: numba
Requires-Dist: numpy
Requires-Dist: pandas
Requires-Dist: pip
Requires-Dist: pydata-sphinx-theme
Requires-Dist: scipy<=1.13.1
Requires-Dist: sphinx
Requires-Dist: sphinx-copybutton
Requires-Dist: sphinx-design
Requires-Dist: sphinx-gallery
Requires-Dist: tqdm
Requires-Dist: zarr<4,>=3
Dynamic: license-file
